{"version":1,"resource":"file:///Users/salvatoredagostino/Dev/yield-mvp/pkg/coinroutesapi/requestentities.go","entries":[{"id":"aPYM.go","timestamp":1653101379222},{"id":"kytY.go","timestamp":1653101415492},{"id":"LD62.go","timestamp":1653101431148},{"id":"GDin.go","timestamp":1653101515510},{"id":"QBgv.go","timestamp":1653101594267},{"id":"kiqQ.go","timestamp":1653101720896},{"id":"JV9P.go","timestamp":1653101807404},{"id":"k36V.go","timestamp":1653108053745},{"id":"lrf8.go","timestamp":1653108098916},{"id":"zwyo.go","timestamp":1653108118401},{"id":"T1FE.go","timestamp":1653108218925},{"id":"4Ywj.go","timestamp":1653108241521},{"id":"ZcDE.go","timestamp":1653245281758},{"id":"bmtx.go","timestamp":1653248087615},{"id":"SySd.go","timestamp":1653493445003},{"id":"miOv.go","timestamp":1653494184954},{"id":"lXCJ.go","timestamp":1653494312876},{"id":"R0oW.go","timestamp":1653494672131},{"id":"P0g1.go","timestamp":1653494773479},{"id":"XVjA.go","timestamp":1653494788643},{"id":"9KVu.go","timestamp":1653497418289},{"id":"epQi.go","timestamp":1653498429629},{"id":"gGxI.go","timestamp":1653498706960},{"id":"BAB7.go","timestamp":1653498731311},{"id":"5tKr.go","timestamp":1653509910934},{"id":"I3FR.go","timestamp":1653510021231},{"id":"AzfK.go","timestamp":1653511633033},{"id":"ijMx.go","timestamp":1653511685328},{"id":"SlGJ.go","timestamp":1653599635185},{"id":"oeL8.go","timestamp":1653600655868},{"id":"JFHv.go","timestamp":1653602072051},{"id":"w2fw.go","timestamp":1653612622348},{"id":"2hvY.go","timestamp":1653612634596},{"id":"Sl30.go","timestamp":1653614014693},{"id":"L5YZ.go","timestamp":1653614035008},{"id":"AaI1.go","timestamp":1653936616104},{"id":"dn33.go","timestamp":1653936639281},{"id":"VJO4.go","timestamp":1653936662138},{"id":"9X6B.go","timestamp":1653938394753},{"id":"roqN.go","timestamp":1653938442807},{"id":"pYKH.go","timestamp":1653938462456},{"id":"3WKh.go","timestamp":1657415553514},{"id":"g1rx.go","timestamp":1657415605086},{"id":"r7xb.go","timestamp":1659152418463},{"id":"lZTg.go","timestamp":1659152510220},{"id":"QGns.go","timestamp":1659152577239},{"id":"5KJl.go","timestamp":1659152644546},{"id":"2KMh.go","timestamp":1659152738246},{"id":"Bd2c.go","timestamp":1659152772577},{"id":"nzUV.go","timestamp":1659152802921}]}