{"version":1,"resource":"file:///Users/salvatoredagostino/Dev/projects/on-air/cmd/on-air/internal/handler/onairhdl.go","entries":[{"id":"T85Y.go","timestamp":1727317537015},{"id":"4ogS.go","timestamp":1727317571680},{"id":"Y1sy.go","timestamp":1727317767182},{"id":"KOcG.go","source":"Organize Imports","timestamp":1727317811081},{"id":"6mpr.go","timestamp":1727318026864},{"id":"suak.go","timestamp":1727318047842},{"id":"MO8b.go","timestamp":1727318131592},{"id":"bXN4.go","timestamp":1727318151177},{"id":"99x5.go","source":"Organize Imports","timestamp":1727318224805},{"id":"aXHQ.go","source":"Organize Imports","timestamp":1727318250296},{"id":"Pe5q.go","timestamp":1727318329630},{"id":"Fg5z.go","timestamp":1727318354612},{"id":"CjsM.go","timestamp":1727319585614},{"id":"2GP7.go","timestamp":1727319599020},{"id":"bebK.go","timestamp":1727320531887},{"id":"RawB.go","timestamp":1727320545968},{"id":"xXGj.go","timestamp":1727320675815}]}